README
setup.cfg
setup.py
python_yelp.egg-info/PKG-INFO
python_yelp.egg-info/SOURCES.txt
python_yelp.egg-info/dependency_links.txt
python_yelp.egg-info/requires.txt
python_yelp.egg-info/top_level.txt
yelp/__init__.py
yelp/api.py