Metadata-Version: 1.0
Name: python-yelp
Version: 0.1.1
Summary: A python client for the Yelp API
Home-page: https://github.com/adamhadani/python-yelp
Author: Adam Ever-Hadani
Author-email: adamhadani@gmail.com
License: Apache License 2.0
Keywords: yelp api
Platform: UNKNOWN
Classifier: Programming Language :: Python
Classifier: Programming Language :: Python :: 2.6
Classifier: Development Status :: 5 - Production/Stable
Classifier: License :: OSI Approved :: Apache Software License
Classifier: Operating System :: POSIX
Classifier: Intended Audience :: Developers
